LICENSE
README.md
setup.py
ANSEncrypt.egg-info/PKG-INFO
ANSEncrypt.egg-info/SOURCES.txt
ANSEncrypt.egg-info/dependency_links.txt
ANSEncrypt.egg-info/top_level.txt
ANSencrypt/__init__.py
ANSencrypt/audio.py
ANSencrypt/image.py
ANSencrypt/text.py
ANSencrypt/video.py