Metadata-Version: 2.1
Name: ANSEncrypt
Version: 1.0.0
Summary: A package for encryption and decryption of images, video, text, and audio
Home-page: https://github.com/saiadupa/ANSEncrypt
Author: Nithin sai Adupa
Author-email: nithinsaiadupa@gmail.com
Classifier: Programming Language :: Python :: 3
Classifier: License :: OSI Approved :: MIT License
Classifier: Operating System :: OS Independent
License-File: LICENSE
